Workbook

Sheet Summary
A1: Hyperscaler AI capex -> accelerator revenue (calendar 2026)
A2: Research agent's model. USD bn. Blue = inputs (Inputs sheet), black = formulas.
A3: Calendar 2026
A4: Output | B4: Bear | C4: Base | D4: Bull | E4: Street | F4: Base vs street | G4: Base vs street %
A5: NVIDIA Data Center revenue | B5: =Model!B4 | C5: =Model!C4 | D5: =Model!D4 | E5: =Model!C5 | F5: =C5-E5 | G5: =F5/E5
A6: AMD Data Center GPU revenue | B6: =Model!B7 | C6: =Model!C7 | D6: =Model!D7 | E6: =Model!C8 | F6: =C6-E6 | G6: =F6/E6
A8: Big-4 2026 capex | C8: =Inputs!C8 | E8: =Inputs!D8 | F8: =C8-E8

Sheet Inputs
A1: Inputs (agent-maintained; every change is logged on the Change log sheet)
A3: Company | B3: Capex measure | C3: Capex (calendar year) | D3: Street | E3: vs street | F3: Sources
A4: Microsoft | B4: Cash additions to property and equipment, calendar 2026 estimate | C4: 150 | D4: =Consensus!B8 | E4: =C4-D4 | F4: street-oct2026
A5: Alphabet | B5: Purchases of property and equipment | C5: 180 | D5: =Consensus!B9 | E5: =C5-D5 | F5: street-oct2026
A6: Meta | B6: Capital expenditures including principal payments on finance leases | C6: 137.5 | D6: =Consensus!B10 | E6: =C6-D6 | F6: street-oct2026
A7: Amazon | B7: Purchases of property and equipment; includes retail fulfillment and transportation | C7: 215 | D7: =Consensus!B11 | E7: =C7-D7 | F7: street-oct2026
A8: Big-4 total | C8: =SUM(C4:C7) | D8: =SUM(D4:D7) | E8: =SUM(E4:E7)
A10: Driver | B10: Bear | C10: Base | D10: Bull | E10: Unit | F10: Notes
A11: Accelerator share of capex | B11: 0.353 | C11: 0.373 | D11: 0.39 | E11: % | F11: accelerator_share
A12: NVIDIA share of accelerator spend | B12: 0.64 | C12: 0.65 | D12: 0.655 | E12: % | F12: nvda_share
A13: AMD share of accelerator spend | B13: 0.025 | C13: 0.0275 | D13: 0.03 | E13: % | F13: amd_share
A14: Big-4 share of NVIDIA DC revenue | B14: 0.4485 | C14: 0.4455 | D14: 0.445 | E14: % | F14: nvda_big4_share
A15: Big-4 share of AMD DC GPU revenue | B15: 0.55 | C15: 0.5 | D15: 0.45 | E15: % | F15: amd_big4_share

Sheet Build
A1: Base-case build-up by customer
A3: Customer | B3: Capex | C3: Accelerator spend | D3: To NVIDIA | E3: To AMD
A4: Microsoft | B4: =Inputs!C4 | C4: =B4*Inputs!$C$11 | D4: =C4*Inputs!$C$12 | E4: =C4*Inputs!$C$13
A5: Alphabet | B5: =Inputs!C5 | C5: =B5*Inputs!$C$11 | D5: =C5*Inputs!$C$12 | E5: =C5*Inputs!$C$13
A6: Meta | B6: =Inputs!C6 | C6: =B6*Inputs!$C$11 | D6: =C6*Inputs!$C$12 | E6: =C6*Inputs!$C$13
A7: Amazon | B7: =Inputs!C7 | C7: =B7*Inputs!$C$11 | D7: =C7*Inputs!$C$12 | E7: =C7*Inputs!$C$13
A8: Big-4 total | B8: =SUM(B4:B7) | C8: =SUM(C4:C7) | D8: =SUM(D4:D7) | E8: =SUM(E4:E7)
A10: Gross-up for non-big-4 customers | D10: =D8/Inputs!$C$14 | E10: =E8/Inputs!$C$15
A11: Implied supplier revenue | D11: =D10 | E11: =E10

Sheet Model
A1: Scenario outputs (calendar 2026, USD bn)
A2: Line | B2: Bear | C2: Base | D2: Bull
A3: Accelerator spend | B3: =Inputs!$C$8*Inputs!B11 | C3: =Inputs!$C$8*Inputs!C11 | D3: =Inputs!$C$8*Inputs!D11
A4: NVIDIA Data Center revenue | B4: =B3*Inputs!B12/Inputs!B14 | C4: =C3*Inputs!C12/Inputs!C14 | D4: =D3*Inputs!D12/Inputs!D14
A5: Street | B5: =Consensus!$B$4 | C5: =Consensus!$B$4 | D5: =Consensus!$B$4
A6: vs street | B6: =B4-B5 | C6: =C4-C5 | D6: =D4-D5
A7: AMD Data Center GPU revenue | B7: =B3*Inputs!B13/Inputs!B15 | C7: =C3*Inputs!C13/Inputs!C15 | D7: =D3*Inputs!D13/Inputs!D15
A8: Street | B8: =Consensus!$B$5 | C8: =Consensus!$B$5 | D8: =Consensus!$B$5
A9: vs street | B9: =B7-B8 | C9: =C7-C8 | D9: =D7-D8

Sheet Quarters
A1: NVIDIA Data Center revenue by fiscal quarter, bridged to calendar 2026
A2: Blue = the agent's inputs: reported quarters (with their source) and its next-quarter estimate. Black = formulas.
A4: Fiscal quarter | B4: Q4 FY26 | C4: Q1 FY27 | D4: Q2 FY27 | E4: Q3 FY27 | F4: Q4 FY27
A5: Months | B5: Nov 2025-Jan 2026 | C5: Feb-Apr 2026 | D5: May-Jul 2026 | E5: Aug-Oct 2026 | F5: Nov 2026-Jan 2027
A6: Status | B6: Reported | C6: Reported | D6: Reported | E6: Estimate | F6: Implied by the model
A7: Data Center revenue | B7: 62.314 | C7: 75.246 | D7: 89.023 | E7: 102 | F7: =IF(COUNT(B7:E7)<4,"",(B12-SUM(B9:E9))/F8)
A8: Months inside calendar 2026 | B8: =1/3 | C8: 1 | D8: 1 | E8: 1 | F8: =2/3
A9: Contribution to calendar 2026 | B9: =IF(B7="","",B7*B8) | C9: =IF(C7="","",C7*C8) | D9: =IF(D7="","",D7*D8) | E9: =IF(E7="","",E7*E8) | F9: =IF(F7="","",F7*F8)
A10: Source | B10: nvda-2026-02-25-cfo | C10: nvda-2026-05-20-cfo | D10: nvda-2026-08-26-cfo | E10: channel-q4-slip
A12: Calendar 2026 Data Center revenue (base model) | B12: =Model!C4
A13: Fiscal Q4 the model requires | B13: =F7
A14: growth on fiscal Q3 | B14: =IF(F7="","",F7/E7-1)
A15: Agent's own fiscal-Q4 view | B15: 127
A16: model needs more (+) or less (-) than that view | B16: =IF(OR(B15="",F7=""),"",F7-B15)

Sheet Consensus
A1: Street consensus as known at the research date (maintained by the app)
A3: Estimate | B3: 2026 (USD bn) | C3: Source
A4: NVIDIA Data Center revenue | B4: 376 | C4: broker-oct2026
A5: AMD Data Center GPU revenue | B5: 14 | C5: broker-oct2026
A8: Microsoft 2026 capex | B8: 145
A9: Alphabet 2026 capex | B9: 175
A10: Meta 2026 capex | B10: 137.5
A11: Amazon 2026 capex | B11: 210

Sheet Change log
A1: Date | B1: Cell | C1: From | D1: To | E1: Why | F1: Sources
A2: 2026-10-12 | B2: Quarters!B7 | D2: 62.314 | E2: Initiate NVIDIA Q3 FY27 Data Center estimate at $103bn: $110.5bn total (2.3% above $108bn guide, smaller than recent beats) less $7.5bn Edge; own Q4 DC view $128bn on Rubin ramp and ACIE growth. Record filing-exact prior Q4/Q1/Q2. | F2: nvda-2026-02-25-cfo
A3: 2026-10-12 | B3: Quarters!C7 | D3: 75.246 | E3: Initiate NVIDIA Q3 FY27 Data Center estimate at $103bn: $110.5bn total (2.3% above $108bn guide, smaller than recent beats) less $7.5bn Edge; own Q4 DC view $128bn on Rubin ramp and ACIE growth. Record filing-exact prior Q4/Q1/Q2. | F3: nvda-2026-05-20-cfo
A4: 2026-10-12 | B4: Quarters!D7 | D4: 89.023 | E4: Initiate NVIDIA Q3 FY27 Data Center estimate at $103bn: $110.5bn total (2.3% above $108bn guide, smaller than recent beats) less $7.5bn Edge; own Q4 DC view $128bn on Rubin ramp and ACIE growth. Record filing-exact prior Q4/Q1/Q2. | F4: nvda-2026-08-26-cfo
A5: 2026-10-12 | B5: Quarters!E7 | D5: 103 | E5: Initiate NVIDIA Q3 FY27 Data Center estimate at $103bn: $110.5bn total (2.3% above $108bn guide, smaller than recent beats) less $7.5bn Edge; own Q4 DC view $128bn on Rubin ramp and ACIE growth. Record filing-exact prior Q4/Q1/Q2. | F5: nvda-2026-08-26-release
A6: 2026-10-12 | B6: Quarters!B15 | D6: 128 | E6: Initiate NVIDIA Q3 FY27 Data Center estimate at $103bn: $110.5bn total (2.3% above $108bn guide, smaller than recent beats) less $7.5bn Edge; own Q4 DC view $128bn on Rubin ramp and ACIE growth. Record filing-exact prior Q4/Q1/Q2.
A7: 2026-10-12 | B7: Inputs!C4 | C7: 145 | D7: 150 | E7: Coverage initiation, calendar 2026: MSFT cash PP&E $150bn ($66.678bn H1 + $83.322bn H2); GOOGL gross PP&E $180bn (available $175-185bn guide midpoint, $80.598bn H1 + $99.402bn H2); AMZN gross PP&E $215bn ($98.411bn H1 + $116.589bn H2), each +$5bn vs street; hold META $137.5bn latest $130-145bn guide midpoint. Keep base mix/NVDA split/concentration 38%/65%/45% as judgment. Tighten NVDA bear mix/split/concentration to 37%/64%/46%, bull to 39%/66%/44.5%: filing-exact CY reported contribution $185.040bn, Q3 DC estimate $103bn and own Q4 $128bn reject initial tails (Q4 required -$32.45bn/$252.01bn at base Q3). AMD GPU-only undisclosed: re-anchor base share 3%->2.7% to street $14bn, narrow bear/bull shares 2%->2.5% and 4.5%->3%; named Meta/Azure deployment supports downside floor but no dollars justify bullish base. All driver sizes are judgment, not reported shares. | F7: msft-2026-04-29-release, msft-2026-07-29-release, googl-2026-02-04-release, googl-2026-07-22-release, meta-2026-04-29-release, meta-2026-07-29-release, amzn-2026-02-05-release, amzn-2026-07-30-release, nvda-2026-02-25-cfo, nvda-2026-05-20-cfo, nvda-2026-05-20-release, nvda-2026-08-26-cfo, nvda-2026-08-26-release, amd-2026-05-05-release, amd-2026-08-04-release, street-oct2026
A8: 2026-10-12 | B8: Inputs!C5 | C8: 175 | D8: 180 | E8: Coverage initiation, calendar 2026: MSFT cash PP&E $150bn ($66.678bn H1 + $83.322bn H2); GOOGL gross PP&E $180bn (available $175-185bn guide midpoint, $80.598bn H1 + $99.402bn H2); AMZN gross PP&E $215bn ($98.411bn H1 + $116.589bn H2), each +$5bn vs street; hold META $137.5bn latest $130-145bn guide midpoint. Keep base mix/NVDA split/concentration 38%/65%/45% as judgment. Tighten NVDA bear mix/split/concentration to 37%/64%/46%, bull to 39%/66%/44.5%: filing-exact CY reported contribution $185.040bn, Q3 DC estimate $103bn and own Q4 $128bn reject initial tails (Q4 required -$32.45bn/$252.01bn at base Q3). AMD GPU-only undisclosed: re-anchor base share 3%->2.7% to street $14bn, narrow bear/bull shares 2%->2.5% and 4.5%->3%; named Meta/Azure deployment supports downside floor but no dollars justify bullish base. All driver sizes are judgment, not reported shares. | F8: msft-2026-04-29-release, msft-2026-07-29-release, googl-2026-02-04-release, googl-2026-07-22-release, meta-2026-04-29-release, meta-2026-07-29-release, amzn-2026-02-05-release, amzn-2026-07-30-release, nvda-2026-02-25-cfo, nvda-2026-05-20-cfo, nvda-2026-05-20-release, nvda-2026-08-26-cfo, nvda-2026-08-26-release, amd-2026-05-05-release, amd-2026-08-04-release, street-oct2026
A9: 2026-10-12 | B9: Inputs!C7 | C9: 210 | D9: 215 | E9: Coverage initiation, calendar 2026: MSFT cash PP&E $150bn ($66.678bn H1 + $83.322bn H2); GOOGL gross PP&E $180bn (available $175-185bn guide midpoint, $80.598bn H1 + $99.402bn H2); AMZN gross PP&E $215bn ($98.411bn H1 + $116.589bn H2), each +$5bn vs street; hold META $137.5bn latest $130-145bn guide midpoint. Keep base mix/NVDA split/concentration 38%/65%/45% as judgment. Tighten NVDA bear mix/split/concentration to 37%/64%/46%, bull to 39%/66%/44.5%: filing-exact CY reported contribution $185.040bn, Q3 DC estimate $103bn and own Q4 $128bn reject initial tails (Q4 required -$32.45bn/$252.01bn at base Q3). AMD GPU-only undisclosed: re-anchor base share 3%->2.7% to street $14bn, narrow bear/bull shares 2%->2.5% and 4.5%->3%; named Meta/Azure deployment supports downside floor but no dollars justify bullish base. All driver sizes are judgment, not reported shares. | F9: msft-2026-04-29-release, msft-2026-07-29-release, googl-2026-02-04-release, googl-2026-07-22-release, meta-2026-04-29-release, meta-2026-07-29-release, amzn-2026-02-05-release, amzn-2026-07-30-release, nvda-2026-02-25-cfo, nvda-2026-05-20-cfo, nvda-2026-05-20-release, nvda-2026-08-26-cfo, nvda-2026-08-26-release, amd-2026-05-05-release, amd-2026-08-04-release, street-oct2026
A10: 2026-10-12 | B10: Inputs!B11 | C10: 0.33 | D10: 0.37 | E10: Coverage initiation, calendar 2026: MSFT cash PP&E $150bn ($66.678bn H1 + $83.322bn H2); GOOGL gross PP&E $180bn (available $175-185bn guide midpoint, $80.598bn H1 + $99.402bn H2); AMZN gross PP&E $215bn ($98.411bn H1 + $116.589bn H2), each +$5bn vs street; hold META $137.5bn latest $130-145bn guide midpoint. Keep base mix/NVDA split/concentration 38%/65%/45% as judgment. Tighten NVDA bear mix/split/concentration to 37%/64%/46%, bull to 39%/66%/44.5%: filing-exact CY reported contribution $185.040bn, Q3 DC estimate $103bn and own Q4 $128bn reject initial tails (Q4 required -$32.45bn/$252.01bn at base Q3). AMD GPU-only undisclosed: re-anchor base share 3%->2.7% to street $14bn, narrow bear/bull shares 2%->2.5% and 4.5%->3%; named Meta/Azure deployment supports downside floor but no dollars justify bullish base. All driver sizes are judgment, not reported shares. | F10: msft-2026-04-29-release, msft-2026-07-29-release, googl-2026-02-04-release, googl-2026-07-22-release, meta-2026-04-29-release, meta-2026-07-29-release, amzn-2026-02-05-release, amzn-2026-07-30-release, nvda-2026-02-25-cfo, nvda-2026-05-20-cfo, nvda-2026-05-20-release, nvda-2026-08-26-cfo, nvda-2026-08-26-release, amd-2026-05-05-release, amd-2026-08-04-release, street-oct2026
A11: 2026-10-12 | B11: Inputs!B12 | C11: 0.58 | D11: 0.64 | E11: Coverage initiation, calendar 2026: MSFT cash PP&E $150bn ($66.678bn H1 + $83.322bn H2); GOOGL gross PP&E $180bn (available $175-185bn guide midpoint, $80.598bn H1 + $99.402bn H2); AMZN gross PP&E $215bn ($98.411bn H1 + $116.589bn H2), each +$5bn vs street; hold META $137.5bn latest $130-145bn guide midpoint. Keep base mix/NVDA split/concentration 38%/65%/45% as judgment. Tighten NVDA bear mix/split/concentration to 37%/64%/46%, bull to 39%/66%/44.5%: filing-exact CY reported contribution $185.040bn, Q3 DC estimate $103bn and own Q4 $128bn reject initial tails (Q4 required -$32.45bn/$252.01bn at base Q3). AMD GPU-only undisclosed: re-anchor base share 3%->2.7% to street $14bn, narrow bear/bull shares 2%->2.5% and 4.5%->3%; named Meta/Azure deployment supports downside floor but no dollars justify bullish base. All driver sizes are judgment, not reported shares. | F11: msft-2026-04-29-release, msft-2026-07-29-release, googl-2026-02-04-release, googl-2026-07-22-release, meta-2026-04-29-release, meta-2026-07-29-release, amzn-2026-02-05-release, amzn-2026-07-30-release, nvda-2026-02-25-cfo, nvda-2026-05-20-cfo, nvda-2026-05-20-release, nvda-2026-08-26-cfo, nvda-2026-08-26-release, amd-2026-05-05-release, amd-2026-08-04-release, street-oct2026
A12: 2026-10-12 | B12: Inputs!B14 | C12: 0.48 | D12: 0.46 | E12: Coverage initiation, calendar 2026: MSFT cash PP&E $150bn ($66.678bn H1 + $83.322bn H2); GOOGL gross PP&E $180bn (available $175-185bn guide midpoint, $80.598bn H1 + $99.402bn H2); AMZN gross PP&E $215bn ($98.411bn H1 + $116.589bn H2), each +$5bn vs street; hold META $137.5bn latest $130-145bn guide midpoint. Keep base mix/NVDA split/concentration 38%/65%/45% as judgment. Tighten NVDA bear mix/split/concentration to 37%/64%/46%, bull to 39%/66%/44.5%: filing-exact CY reported contribution $185.040bn, Q3 DC estimate $103bn and own Q4 $128bn reject initial tails (Q4 required -$32.45bn/$252.01bn at base Q3). AMD GPU-only undisclosed: re-anchor base share 3%->2.7% to street $14bn, narrow bear/bull shares 2%->2.5% and 4.5%->3%; named Meta/Azure deployment supports downside floor but no dollars justify bullish base. All driver sizes are judgment, not reported shares. | F12: msft-2026-04-29-release, msft-2026-07-29-release, googl-2026-02-04-release, googl-2026-07-22-release, meta-2026-04-29-release, meta-2026-07-29-release, amzn-2026-02-05-release, amzn-2026-07-30-release, nvda-2026-02-25-cfo, nvda-2026-05-20-cfo, nvda-2026-05-20-release, nvda-2026-08-26-cfo, nvda-2026-08-26-release, amd-2026-05-05-release, amd-2026-08-04-release, street-oct2026
A13: 2026-10-12 | B13: Inputs!D11 | C13: 0.42 | D13: 0.39 | E13: Coverage initiation, calendar 2026: MSFT cash PP&E $150bn ($66.678bn H1 + $83.322bn H2); GOOGL gross PP&E $180bn (available $175-185bn guide midpoint, $80.598bn H1 + $99.402bn H2); AMZN gross PP&E $215bn ($98.411bn H1 + $116.589bn H2), each +$5bn vs street; hold META $137.5bn latest $130-145bn guide midpoint. Keep base mix/NVDA split/concentration 38%/65%/45% as judgment. Tighten NVDA bear mix/split/concentration to 37%/64%/46%, bull to 39%/66%/44.5%: filing-exact CY reported contribution $185.040bn, Q3 DC estimate $103bn and own Q4 $128bn reject initial tails (Q4 required -$32.45bn/$252.01bn at base Q3). AMD GPU-only undisclosed: re-anchor base share 3%->2.7% to street $14bn, narrow bear/bull shares 2%->2.5% and 4.5%->3%; named Meta/Azure deployment supports downside floor but no dollars justify bullish base. All driver sizes are judgment, not reported shares. | F13: msft-2026-04-29-release, msft-2026-07-29-release, googl-2026-02-04-release, googl-2026-07-22-release, meta-2026-04-29-release, meta-2026-07-29-release, amzn-2026-02-05-release, amzn-2026-07-30-release, nvda-2026-02-25-cfo, nvda-2026-05-20-cfo, nvda-2026-05-20-release, nvda-2026-08-26-cfo, nvda-2026-08-26-release, amd-2026-05-05-release, amd-2026-08-04-release, street-oct2026
A14: 2026-10-12 | B14: Inputs!D12 | C14: 0.7 | D14: 0.66 | E14: Coverage initiation, calendar 2026: MSFT cash PP&E $150bn ($66.678bn H1 + $83.322bn H2); GOOGL gross PP&E $180bn (available $175-185bn guide midpoint, $80.598bn H1 + $99.402bn H2); AMZN gross PP&E $215bn ($98.411bn H1 + $116.589bn H2), each +$5bn vs street; hold META $137.5bn latest $130-145bn guide midpoint. Keep base mix/NVDA split/concentration 38%/65%/45% as judgment. Tighten NVDA bear mix/split/concentration to 37%/64%/46%, bull to 39%/66%/44.5%: filing-exact CY reported contribution $185.040bn, Q3 DC estimate $103bn and own Q4 $128bn reject initial tails (Q4 required -$32.45bn/$252.01bn at base Q3). AMD GPU-only undisclosed: re-anchor base share 3%->2.7% to street $14bn, narrow bear/bull shares 2%->2.5% and 4.5%->3%; named Meta/Azure deployment supports downside floor but no dollars justify bullish base. All driver sizes are judgment, not reported shares. | F14: msft-2026-04-29-release, msft-2026-07-29-release, googl-2026-02-04-release, googl-2026-07-22-release, meta-2026-04-29-release, meta-2026-07-29-release, amzn-2026-02-05-release, amzn-2026-07-30-release, nvda-2026-02-25-cfo, nvda-2026-05-20-cfo, nvda-2026-05-20-release, nvda-2026-08-26-cfo, nvda-2026-08-26-release, amd-2026-05-05-release, amd-2026-08-04-release, street-oct2026
A15: 2026-10-12 | B15: Inputs!D14 | C15: 0.43 | D15: 0.445 | E15: Coverage initiation, calendar 2026: MSFT cash PP&E $150bn ($66.678bn H1 + $83.322bn H2); GOOGL gross PP&E $180bn (available $175-185bn guide midpoint, $80.598bn H1 + $99.402bn H2); AMZN gross PP&E $215bn ($98.411bn H1 + $116.589bn H2), each +$5bn vs street; hold META $137.5bn latest $130-145bn guide midpoint. Keep base mix/NVDA split/concentration 38%/65%/45% as judgment. Tighten NVDA bear mix/split/concentration to 37%/64%/46%, bull to 39%/66%/44.5%: filing-exact CY reported contribution $185.040bn, Q3 DC estimate $103bn and own Q4 $128bn reject initial tails (Q4 required -$32.45bn/$252.01bn at base Q3). AMD GPU-only undisclosed: re-anchor base share 3%->2.7% to street $14bn, narrow bear/bull shares 2%->2.5% and 4.5%->3%; named Meta/Azure deployment supports downside floor but no dollars justify bullish base. All driver sizes are judgment, not reported shares. | F15: msft-2026-04-29-release, msft-2026-07-29-release, googl-2026-02-04-release, googl-2026-07-22-release, meta-2026-04-29-release, meta-2026-07-29-release, amzn-2026-02-05-release, amzn-2026-07-30-release, nvda-2026-02-25-cfo, nvda-2026-05-20-cfo, nvda-2026-05-20-release, nvda-2026-08-26-cfo, nvda-2026-08-26-release, amd-2026-05-05-release, amd-2026-08-04-release, street-oct2026
A16: 2026-10-12 | B16: Inputs!B13 | C16: 0.02 | D16: 0.025 | E16: Coverage initiation, calendar 2026: MSFT cash PP&E $150bn ($66.678bn H1 + $83.322bn H2); GOOGL gross PP&E $180bn (available $175-185bn guide midpoint, $80.598bn H1 + $99.402bn H2); AMZN gross PP&E $215bn ($98.411bn H1 + $116.589bn H2), each +$5bn vs street; hold META $137.5bn latest $130-145bn guide midpoint. Keep base mix/NVDA split/concentration 38%/65%/45% as judgment. Tighten NVDA bear mix/split/concentration to 37%/64%/46%, bull to 39%/66%/44.5%: filing-exact CY reported contribution $185.040bn, Q3 DC estimate $103bn and own Q4 $128bn reject initial tails (Q4 required -$32.45bn/$252.01bn at base Q3). AMD GPU-only undisclosed: re-anchor base share 3%->2.7% to street $14bn, narrow bear/bull shares 2%->2.5% and 4.5%->3%; named Meta/Azure deployment supports downside floor but no dollars justify bullish base. All driver sizes are judgment, not reported shares. | F16: msft-2026-04-29-release, msft-2026-07-29-release, googl-2026-02-04-release, googl-2026-07-22-release, meta-2026-04-29-release, meta-2026-07-29-release, amzn-2026-02-05-release, amzn-2026-07-30-release, nvda-2026-02-25-cfo, nvda-2026-05-20-cfo, nvda-2026-05-20-release, nvda-2026-08-26-cfo, nvda-2026-08-26-release, amd-2026-05-05-release, amd-2026-08-04-release, street-oct2026
A17: 2026-10-12 | B17: Inputs!C13 | C17: 0.03 | D17: 0.027 | E17: Coverage initiation, calendar 2026: MSFT cash PP&E $150bn ($66.678bn H1 + $83.322bn H2); GOOGL gross PP&E $180bn (available $175-185bn guide midpoint, $80.598bn H1 + $99.402bn H2); AMZN gross PP&E $215bn ($98.411bn H1 + $116.589bn H2), each +$5bn vs street; hold META $137.5bn latest $130-145bn guide midpoint. Keep base mix/NVDA split/concentration 38%/65%/45% as judgment. Tighten NVDA bear mix/split/concentration to 37%/64%/46%, bull to 39%/66%/44.5%: filing-exact CY reported contribution $185.040bn, Q3 DC estimate $103bn and own Q4 $128bn reject initial tails (Q4 required -$32.45bn/$252.01bn at base Q3). AMD GPU-only undisclosed: re-anchor base share 3%->2.7% to street $14bn, narrow bear/bull shares 2%->2.5% and 4.5%->3%; named Meta/Azure deployment supports downside floor but no dollars justify bullish base. All driver sizes are judgment, not reported shares. | F17: msft-2026-04-29-release, msft-2026-07-29-release, googl-2026-02-04-release, googl-2026-07-22-release, meta-2026-04-29-release, meta-2026-07-29-release, amzn-2026-02-05-release, amzn-2026-07-30-release, nvda-2026-02-25-cfo, nvda-2026-05-20-cfo, nvda-2026-05-20-release, nvda-2026-08-26-cfo, nvda-2026-08-26-release, amd-2026-05-05-release, amd-2026-08-04-release, street-oct2026
A18: 2026-10-12 | B18: Inputs!D13 | C18: 0.045 | D18: 0.03 | E18: Coverage initiation, calendar 2026: MSFT cash PP&E $150bn ($66.678bn H1 + $83.322bn H2); GOOGL gross PP&E $180bn (available $175-185bn guide midpoint, $80.598bn H1 + $99.402bn H2); AMZN gross PP&E $215bn ($98.411bn H1 + $116.589bn H2), each +$5bn vs street; hold META $137.5bn latest $130-145bn guide midpoint. Keep base mix/NVDA split/concentration 38%/65%/45% as judgment. Tighten NVDA bear mix/split/concentration to 37%/64%/46%, bull to 39%/66%/44.5%: filing-exact CY reported contribution $185.040bn, Q3 DC estimate $103bn and own Q4 $128bn reject initial tails (Q4 required -$32.45bn/$252.01bn at base Q3). AMD GPU-only undisclosed: re-anchor base share 3%->2.7% to street $14bn, narrow bear/bull shares 2%->2.5% and 4.5%->3%; named Meta/Azure deployment supports downside floor but no dollars justify bullish base. All driver sizes are judgment, not reported shares. | F18: msft-2026-04-29-release, msft-2026-07-29-release, googl-2026-02-04-release, googl-2026-07-22-release, meta-2026-04-29-release, meta-2026-07-29-release, amzn-2026-02-05-release, amzn-2026-07-30-release, nvda-2026-02-25-cfo, nvda-2026-05-20-cfo, nvda-2026-05-20-release, nvda-2026-08-26-cfo, nvda-2026-08-26-release, amd-2026-05-05-release, amd-2026-08-04-release, street-oct2026
A19: 2026-10-12 | B19: Quarters!B15 | C19: 128 | D19: 128 | E19: After initiating inputs, retain unreported Q3 FY27 Data Center $103bn and own Q4 FY27 $128bn. Q3 total $110.5bn less Edge $7.5bn; total beats guide 2.3%, below recent 4.6%/5.7% beats. Calendar bridge weights prior Q4 by 1/3, Q1/Q2/Q3 by 1, next Q4 by 2/3. Record expected Q3 print November 18, 2026 as analyst estimate, unconfirmed.
A20: 2026-10-12 | B20: Inputs!D12 | C20: 0.66 | D20: 0.655 | E20: October 12 synthetic channel check: October 1-8 interviews add an apparently distinct order-channel observation of rising custom accelerators at two unnamed Big Four clouds, but respondent independence, customer identity, dollars and delivery years are unverified. Prior Amazon primary disclosures independently establish Trainium deployments and 2027 capacity plans, not the anonymous customers' dollar shares. As judgment, halve the optional NVIDIA bull share premium over base from 1pp to 0.5pp: bull nvda_share 66%->65.5%, cutting CY2026 bull $394.78bn to $391.79bn (-$2.99bn/-0.76%). This discounts favorable end-year share persistence, not a measured 2026 market-share loss or a mechanical import of 2027 orders. Hold base/bear shares, all company capex, mix, concentration, AMD and Q3/Q4 estimates: 2027 power constraint is one planner's account without a dated slip; stable neocloud 20-30 week lead times are not new slippage. Base $374.62bn, Q3 DC $103bn and own Q4 $128bn remain. | F20: channel-oct2026, amzn-2026-02-05-release, amzn-2026-04-29-release, amzn-2026-07-30-release, nvda-2026-08-26-release
A21: 2026-10-12 | B21: Inputs!C11 | C21: 0.38 | D21: 0.373 | E21: Dated synthetic calendar-Q4-to-Q1 deferral allegations change timing odds despite unverified respondent independence and customer IDs. System value $12-15bn x reported 70% NVIDIA is $8.4-10.5bn branded rack value, not NVIDIA revenue. Size direct total-NVIDIA base haircut at about $3.15bn: $13.5bn midpoint x70% x assumed 2/3 supplier content x50% net confidence/recognition-shift weight; bear about $7.56bn uses 80% content and full realization. These conversion/weights are judgment, not disclosed BOM or probabilities. Base mix 38%->37.3% and NVDA Big4 concentration 45%->44.55% jointly calibrate ~$3.19bn direct global hit while keeping non-Big4 NVDA dollars approximately unchanged; do not gross a customer-specific loss up by 1/concentration. Bear mix 37%->35.3%, concentration46%->44.85% give ~$7.55bn hit. Base AMD split2.7%->2.75% recalibrates unchanged ~$14bn GPU anchor after shared-mix change; no claim of competitive share gain. Hold all company capex estimates pending IDs/measure reconciliation; lower realized accelerator mix is a provisional timing proxy assuming other infrastructure/prepaid/offset deliveries can fill current budgets, not a measured cash-capex cut. If named cash cuts are confirmed replace/reconcile the proxy to avoid double counting. Hold NVIDIA competitive split and bull. Separate quarterly tool revises Q3DC103->102 and own Q4DC128->127: roughly even original Oct-Dec and new Jan-Mar placement makes expected ~$1.05bn net hit to each fiscal quarter; January remains FYQ4. | F21: channel-q4-slip, channel-oct2026, web-b93e425ae9, web-81e32d74b6, web-454ed8f95a, meta-2026-07-29-release, nvda-2026-08-26-release, amd-2026-08-04-release
A22: 2026-10-12 | B22: Inputs!C14 | C22: 0.45 | D22: 0.4455 | E22: Dated synthetic calendar-Q4-to-Q1 deferral allegations change timing odds despite unverified respondent independence and customer IDs. System value $12-15bn x reported 70% NVIDIA is $8.4-10.5bn branded rack value, not NVIDIA revenue. Size direct total-NVIDIA base haircut at about $3.15bn: $13.5bn midpoint x70% x assumed 2/3 supplier content x50% net confidence/recognition-shift weight; bear about $7.56bn uses 80% content and full realization. These conversion/weights are judgment, not disclosed BOM or probabilities. Base mix 38%->37.3% and NVDA Big4 concentration 45%->44.55% jointly calibrate ~$3.19bn direct global hit while keeping non-Big4 NVDA dollars approximately unchanged; do not gross a customer-specific loss up by 1/concentration. Bear mix 37%->35.3%, concentration46%->44.85% give ~$7.55bn hit. Base AMD split2.7%->2.75% recalibrates unchanged ~$14bn GPU anchor after shared-mix change; no claim of competitive share gain. Hold all company capex estimates pending IDs/measure reconciliation; lower realized accelerator mix is a provisional timing proxy assuming other infrastructure/prepaid/offset deliveries can fill current budgets, not a measured cash-capex cut. If named cash cuts are confirmed replace/reconcile the proxy to avoid double counting. Hold NVIDIA competitive split and bull. Separate quarterly tool revises Q3DC103->102 and own Q4DC128->127: roughly even original Oct-Dec and new Jan-Mar placement makes expected ~$1.05bn net hit to each fiscal quarter; January remains FYQ4. | F22: channel-q4-slip, channel-oct2026, web-b93e425ae9, web-81e32d74b6, web-454ed8f95a, meta-2026-07-29-release, nvda-2026-08-26-release, amd-2026-08-04-release
A23: 2026-10-12 | B23: Inputs!C13 | C23: 0.027 | D23: 0.0275 | E23: Dated synthetic calendar-Q4-to-Q1 deferral allegations change timing odds despite unverified respondent independence and customer IDs. System value $12-15bn x reported 70% NVIDIA is $8.4-10.5bn branded rack value, not NVIDIA revenue. Size direct total-NVIDIA base haircut at about $3.15bn: $13.5bn midpoint x70% x assumed 2/3 supplier content x50% net confidence/recognition-shift weight; bear about $7.56bn uses 80% content and full realization. These conversion/weights are judgment, not disclosed BOM or probabilities. Base mix 38%->37.3% and NVDA Big4 concentration 45%->44.55% jointly calibrate ~$3.19bn direct global hit while keeping non-Big4 NVDA dollars approximately unchanged; do not gross a customer-specific loss up by 1/concentration. Bear mix 37%->35.3%, concentration46%->44.85% give ~$7.55bn hit. Base AMD split2.7%->2.75% recalibrates unchanged ~$14bn GPU anchor after shared-mix change; no claim of competitive share gain. Hold all company capex estimates pending IDs/measure reconciliation; lower realized accelerator mix is a provisional timing proxy assuming other infrastructure/prepaid/offset deliveries can fill current budgets, not a measured cash-capex cut. If named cash cuts are confirmed replace/reconcile the proxy to avoid double counting. Hold NVIDIA competitive split and bull. Separate quarterly tool revises Q3DC103->102 and own Q4DC128->127: roughly even original Oct-Dec and new Jan-Mar placement makes expected ~$1.05bn net hit to each fiscal quarter; January remains FYQ4. | F23: channel-q4-slip, channel-oct2026, web-b93e425ae9, web-81e32d74b6, web-454ed8f95a, meta-2026-07-29-release, nvda-2026-08-26-release, amd-2026-08-04-release
A24: 2026-10-12 | B24: Inputs!B11 | C24: 0.37 | D24: 0.353 | E24: Dated synthetic calendar-Q4-to-Q1 deferral allegations change timing odds despite unverified respondent independence and customer IDs. System value $12-15bn x reported 70% NVIDIA is $8.4-10.5bn branded rack value, not NVIDIA revenue. Size direct total-NVIDIA base haircut at about $3.15bn: $13.5bn midpoint x70% x assumed 2/3 supplier content x50% net confidence/recognition-shift weight; bear about $7.56bn uses 80% content and full realization. These conversion/weights are judgment, not disclosed BOM or probabilities. Base mix 38%->37.3% and NVDA Big4 concentration 45%->44.55% jointly calibrate ~$3.19bn direct global hit while keeping non-Big4 NVDA dollars approximately unchanged; do not gross a customer-specific loss up by 1/concentration. Bear mix 37%->35.3%, concentration46%->44.85% give ~$7.55bn hit. Base AMD split2.7%->2.75% recalibrates unchanged ~$14bn GPU anchor after shared-mix change; no claim of competitive share gain. Hold all company capex estimates pending IDs/measure reconciliation; lower realized accelerator mix is a provisional timing proxy assuming other infrastructure/prepaid/offset deliveries can fill current budgets, not a measured cash-capex cut. If named cash cuts are confirmed replace/reconcile the proxy to avoid double counting. Hold NVIDIA competitive split and bull. Separate quarterly tool revises Q3DC103->102 and own Q4DC128->127: roughly even original Oct-Dec and new Jan-Mar placement makes expected ~$1.05bn net hit to each fiscal quarter; January remains FYQ4. | F24: channel-q4-slip, channel-oct2026, web-b93e425ae9, web-81e32d74b6, web-454ed8f95a, meta-2026-07-29-release, nvda-2026-08-26-release, amd-2026-08-04-release
A25: 2026-10-12 | B25: Inputs!B14 | C25: 0.46 | D25: 0.4485 | E25: Dated synthetic calendar-Q4-to-Q1 deferral allegations change timing odds despite unverified respondent independence and customer IDs. System value $12-15bn x reported 70% NVIDIA is $8.4-10.5bn branded rack value, not NVIDIA revenue. Size direct total-NVIDIA base haircut at about $3.15bn: $13.5bn midpoint x70% x assumed 2/3 supplier content x50% net confidence/recognition-shift weight; bear about $7.56bn uses 80% content and full realization. These conversion/weights are judgment, not disclosed BOM or probabilities. Base mix 38%->37.3% and NVDA Big4 concentration 45%->44.55% jointly calibrate ~$3.19bn direct global hit while keeping non-Big4 NVDA dollars approximately unchanged; do not gross a customer-specific loss up by 1/concentration. Bear mix 37%->35.3%, concentration46%->44.85% give ~$7.55bn hit. Base AMD split2.7%->2.75% recalibrates unchanged ~$14bn GPU anchor after shared-mix change; no claim of competitive share gain. Hold all company capex estimates pending IDs/measure reconciliation; lower realized accelerator mix is a provisional timing proxy assuming other infrastructure/prepaid/offset deliveries can fill current budgets, not a measured cash-capex cut. If named cash cuts are confirmed replace/reconcile the proxy to avoid double counting. Hold NVIDIA competitive split and bull. Separate quarterly tool revises Q3DC103->102 and own Q4DC128->127: roughly even original Oct-Dec and new Jan-Mar placement makes expected ~$1.05bn net hit to each fiscal quarter; January remains FYQ4. | F25: channel-q4-slip, channel-oct2026, web-b93e425ae9, web-81e32d74b6, web-454ed8f95a, meta-2026-07-29-release, nvda-2026-08-26-release, amd-2026-08-04-release
A26: 2026-10-12 | B26: Quarters!E7 | C26: 103 | D26: 102 | E26: Revise unreported Q3 FY27 Data Center 103->102 and own Q4 FY27 128->127 on dated Q4 CY2026 rack deferrals. Direct expected calendar revenue shift ~$3.15bn is judgment from branded-value/content/net-realization assumptions. Assume original shifted supplier revenue roughly evenly in Oct/Nov/Dec and receipts Jan/Feb/Mar: Q3 loses October ~$1.05bn; FYQ4 loses Nov/Dec ~$2.10bn but gains January ~$1.05bn, net loss ~$1.05bn, rounded to $1bn each. These month allocations are estimates, not vendor detail. New Q3 total109.5 less Edge7.5 is a1.4% beat vs108 guide. Expected Nov18 report remains unconfirmed. Filing-exact reported quarters unchanged. New top-down annual371.4301 implies FYQ4 126.5847 at revised Q3 102; own127 yields monthly bridge371.707. Fixed monthly weights cannot fully measure January redistribution; saved formulas/application recalculation, not pre-decision snapshot diagnostics, govern. | F26: channel-q4-slip
A27: 2026-10-12 | B27: Quarters!B15 | C27: 128 | D27: 127 | E27: Revise unreported Q3 FY27 Data Center 103->102 and own Q4 FY27 128->127 on dated Q4 CY2026 rack deferrals. Direct expected calendar revenue shift ~$3.15bn is judgment from branded-value/content/net-realization assumptions. Assume original shifted supplier revenue roughly evenly in Oct/Nov/Dec and receipts Jan/Feb/Mar: Q3 loses October ~$1.05bn; FYQ4 loses Nov/Dec ~$2.10bn but gains January ~$1.05bn, net loss ~$1.05bn, rounded to $1bn each. These month allocations are estimates, not vendor detail. New Q3 total109.5 less Edge7.5 is a1.4% beat vs108 guide. Expected Nov18 report remains unconfirmed. Filing-exact reported quarters unchanged. New top-down annual371.4301 implies FYQ4 126.5847 at revised Q3 102; own127 yields monthly bridge371.707. Fixed monthly weights cannot fully measure January redistribution; saved formulas/application recalculation, not pre-decision snapshot diagnostics, govern.
